oscar_ai/__init__.py
oscar_ai/actions/__init__.py
oscar_ai/actions/speak.py
oscar_ai-0.0.3.dist-info/LICENSE
oscar_ai-0.0.3.dist-info/METADATA
oscar_ai-0.0.3.dist-info/WHEEL
oscar_ai-0.0.3.dist-info/top_level.txt
oscar_ai-0.0.3.dist-info/RECORD
