Metadata-Version: 2.1
Name: oscar-ai
Version: 0.0.3
Summary: TODO
Home-page: https://github.com/TODO
Author: Oscar Lopez
Author-email: olopezdeveloper@gmail.com
License: UNKNOWN
Project-URL: Bug Tracker, https://github.com/TODO
Platform: UNKNOWN
Classifier: Programming Language :: Python :: 3
Classifier: License :: OSI Approved :: MIT License
Classifier: Operating System :: OS Independent
Requires-Python: >=3.9
License-File: LICENSE
